qtoggleserver/mqtt/__init__.py
qtoggleserver/mqtt/mqtteventhandler.py
qtoggleserver_mqtt-1.3.0.dist-info/licenses/LICENSE.txt
qtoggleserver_mqtt-1.3.0.dist-info/METADATA
qtoggleserver_mqtt-1.3.0.dist-info/WHEEL
qtoggleserver_mqtt-1.3.0.dist-info/top_level.txt
qtoggleserver_mqtt-1.3.0.dist-info/RECORD
