Metadata-Version: 2.4
Name: qtoggleserver-mqtt
Version: 1.3.0
Summary: Publish qToggleServer events to an MQTT broker
Author-email: Calin Crisan <ccrisan@gmail.com>
License: Apache 2.0
Requires-Python: >=3.11
License-File: LICENSE.txt
Requires-Dist: aiomqtt
Dynamic: license-file
